waterlooworks/__init__.py
waterlooworks/anon.py
waterlooworks/pdf_redactor.py
waterlooworks-0.0.1.data/scripts/waterlooworks
waterlooworks-0.0.1.data/scripts/waterlooworks-grep
waterlooworks-0.0.1.dist-info/METADATA
waterlooworks-0.0.1.dist-info/RECORD
waterlooworks-0.0.1.dist-info/WHEEL
waterlooworks-0.0.1.dist-info/top_level.txt
