Metadata-Version: 2.1
Name: waterlooworks
Version: 0.0.1
Summary: Package and scripts for interacting with Waterloo Works
Home-page: https://github.com/dang3r/waterlooworks
Author: Daniel Cardoza
Author-email: dan@danielcardoza.com
License: MIT
Platform: UNKNOWN
Requires-Python: >=3.4.0
Requires-Dist: click (==7.0)
Requires-Dist: textmining
Requires-Dist: pdfrw
